setup.cfg
setup.py
seaborn/__init__.py
seaborn/calling_function.py
seaborn_calling_function.egg-info/PKG-INFO
seaborn_calling_function.egg-info/SOURCES.txt
seaborn_calling_function.egg-info/dependency_links.txt
seaborn_calling_function.egg-info/top_level.txt
test/test_calling_function.py