Metadata-Version: 1.1
Name: seaborn-calling-function
Version: 0.0.2
Summary: SeabornCallingFunction reads metadata regarding functions applied to its member functions."
Home-page: https://github.com/christensonb/SeabornCallingFunction
Author: Ben Christenson
Author-email: Python@BenChristenson.com
License: MIT License
Download-URL: https://github.com/christensonb/SeabornCallingFunction/tarball/download
Keywords: metadata
Platform: UNKNOWN
Classifier: Intended Audience :: Developers
Classifier: Natural Language :: English
Classifier: License :: Other/Proprietary License
Classifier: Operating System :: POSIX :: Linux
Classifier: Programming Language :: Python
Classifier: Programming Language :: Python :: 2.7
Classifier: Programming Language :: Python :: 3.6
